[
  [
    {
      "year": 2025,
      "month": 4,
      "day": 27,
      "extraInfo": "三十",
      "monthStartWeekIndex": 0,
      "monthEndWeekIndex": 5,
      "shiftType": 1,
      "agenda": []
    },
    {
      "year": 2025,
      "month": 4,
      "day": 28,
      "extraInfo": "四月",
      "monthStartWeekIndex": 0,
      "monthEndWeekIndex": 5,
      "shiftType": 0,
      "agenda": []
    },
    {
      "year": 2025,
      "month": 4,
      "day": 29,
      "extraInfo": "初二",
      "monthStartWeekIndex": 0,
      "monthEndWeekIndex": 5,
      "shiftType": 0,
      "agenda": []
    },
    {
      "year": 2025,
      "month": 4,
      "day": 30,
      "extraInfo": "初三",
      "monthStartWeekIndex": 0,
      "monthEndWeekIndex": 5,
      "shiftType": 0,
      "agenda": []
    },
    {
      "year": 2025,
      "month": 5,
      "day": 1,
      "extraInfo": "劳动节",
      "monthStartWeekIndex": 0,
      "monthEndWeekIndex": 5,
      "shiftType": 2,
      "agenda": []
    },
    {
      "year": 2025,
      "month": 5,
      "day": 2,
      "extraInfo": "初五",
      "monthStartWeekIndex": 0,
      "monthEndWeekIndex": 5,
      "shiftType": 2,
      "agenda": []
    },
    {
      "year": 2025,
      "month": 5,
      "day": 3,
      "extraInfo": "初六",
      "monthStartWeekIndex": 0,
      "monthEndWeekIndex": 5,
      "shiftType": 2,
      "agenda": []
    }
  ],
  [
    {
      "year": 2025,
      "month": 5,
      "day": 4,
      "extraInfo": "青年节",
      "monthStartWeekIndex": 0,
      "monthEndWeekIndex": 5,
      "shiftType": 2,
      "agenda": []
    },
    {
      "year": 2025,
      "month": 5,
      "day": 5,
      "extraInfo": "立夏",
      "monthStartWeekIndex": 0,
      "monthEndWeekIndex": 5,
      "shiftType": 2,
      "agenda": []
    },
    {
      "year": 2025,
      "month": 5,
      "day": 6,
      "extraInfo": "初九",
      "monthStartWeekIndex": 0,
      "monthEndWeekIndex": 5,
      "shiftType": 0,
      "agenda": []
    },
    {
      "year": 2025,
      "month": 5,
      "day": 7,
      "extraInfo": "初十",
      "monthStartWeekIndex": 0,
      "monthEndWeekIndex": 5,
      "shiftType": 0,
      "agenda": []
    },
    {
      "year": 2025,
      "month": 5,
      "day": 8,
      "extraInfo": "十一",
      "monthStartWeekIndex": 0,
      "monthEndWeekIndex": 5,
      "shiftType": 0,
      "agenda": []
    },
    {
      "year": 2025,
      "month": 5,
      "day": 9,
      "extraInfo": "十二",
      "monthStartWeekIndex": 0,
      "monthEndWeekIndex": 5,
      "shiftType": 0,
      "agenda": []
    },
    {
      "year": 2025,
      "month": 5,
      "day": 10,
      "extraInfo": "十三",
      "monthStartWeekIndex": 0,
      "monthEndWeekIndex": 5,
      "shiftType": 0,
      "agenda": []
    }
  ],
  [
    {
      "year": 2025,
      "month": 5,
      "day": 11,
      "extraInfo": "十四",
      "monthStartWeekIndex": 0,
      "monthEndWeekIndex": 5,
      "shiftType": 0,
      "agenda": []
    },
    {
      "year": 2025,
      "month": 5,
      "day": 12,
      "extraInfo": "十五",
      "monthStartWeekIndex": 0,
      "monthEndWeekIndex": 5,
      "shiftType": 0,
      "agenda": []
    },
    {
      "year": 2025,
      "month": 5,
      "day": 13,
      "extraInfo": "十六",
      "monthStartWeekIndex": 0,
      "monthEndWeekIndex": 5,
      "shiftType": 0,
      "agenda": []
    },
    {
      "year": 2025,
      "month": 5,
      "day": 14,
      "extraInfo": "十七",
      "monthStartWeekIndex": 0,
      "monthEndWeekIndex": 5,
      "shiftType": 0,
      "agenda": []
    },
    {
      "year": 2025,
      "month": 5,
      "day": 15,
      "extraInfo": "十八",
      "monthStartWeekIndex": 0,
      "monthEndWeekIndex": 5,
      "shiftType": 0,
      "agenda": [
        {
          "time": "13:00",
          "activity": "阅读"
        }
      ]
    },
    {
      "year": 2025,
      "month": 5,
      "day": 16,
      "extraInfo": "十九",
      "monthStartWeekIndex": 0,
      "monthEndWeekIndex": 5,
      "shiftType": 0,
      "agenda": []
    },
    {
      "year": 2025,
      "month": 5,
      "day": 17,
      "extraInfo": "二十",
      "monthStartWeekIndex": 0,
      "monthEndWeekIndex": 5,
      "shiftType": 0,
      "agenda": []
    }
  ],
  [
    {
      "year": 2025,
      "month": 5,
      "day": 18,
      "extraInfo": "廿一",
      "monthStartWeekIndex": 0,
      "monthEndWeekIndex": 5,
      "shiftType": 0,
      "agenda": []
    },
    {
      "year": 2025,
      "month": 5,
      "day": 19,
      "extraInfo": "廿二",
      "monthStartWeekIndex": 0,
      "monthEndWeekIndex": 5,
      "shiftType": 0,
      "agenda": []
    },
    {
      "year": 2025,
      "month": 5,
      "day": 20,
      "extraInfo": "廿三",
      "monthStartWeekIndex": 0,
      "monthEndWeekIndex": 5,
      "shiftType": 0,
      "agenda": [
        {
          "time": "14:30",
          "activity": "拜访客户"
        }
      ]
    },
    {
      "year": 2025,
      "month": 5,
      "day": 21,
      "extraInfo": "小满",
      "monthStartWeekIndex": 0,
      "monthEndWeekIndex": 5,
      "shiftType": 0,
      "agenda": []
    },
    {
      "year": 2025,
      "month": 5,
      "day": 22,
      "extraInfo": "廿五",
      "monthStartWeekIndex": 0,
      "monthEndWeekIndex": 5,
      "shiftType": 0,
      "agenda": []
    },
    {
      "year": 2025,
      "month": 5,
      "day": 23,
      "extraInfo": "廿六",
      "monthStartWeekIndex": 0,
      "monthEndWeekIndex": 5,
      "shiftType": 0,
      "agenda": []
    },
    {
      "year": 2025,
      "month": 5,
      "day": 24,
      "extraInfo": "廿七",
      "monthStartWeekIndex": 0,
      "monthEndWeekIndex": 5,
      "shiftType": 0,
      "agenda": []
    }
  ],
  [
    {
      "year": 2025,
      "month": 5,
      "day": 25,
      "extraInfo": "廿八",
      "monthStartWeekIndex": 0,
      "monthEndWeekIndex": 5,
      "shiftType": 0,
      "agenda": []
    },
    {
      "year": 2025,
      "month": 5,
      "day": 26,
      "extraInfo": "廿九",
      "monthStartWeekIndex": 0,
      "monthEndWeekIndex": 5,
      "shiftType": 0,
      "agenda": []
    },
    {
      "year": 2025,
      "month": 5,
      "day": 27,
      "extraInfo": "五月",
      "monthStartWeekIndex": 0,
      "monthEndWeekIndex": 5,
      "shiftType": 0,
      "agenda": []
    },
    {
      "year": 2025,
      "month": 5,
      "day": 28,
      "extraInfo": "初二",
      "monthStartWeekIndex": 0,
      "monthEndWeekIndex": 5,
      "shiftType": 0,
      "agenda": []
    },
    {
      "year": 2025,
      "month": 5,
      "day": 29,
      "extraInfo": "初三",
      "monthStartWeekIndex": 0,
      "monthEndWeekIndex": 5,
      "shiftType": 0,
      "agenda": []
    },
    {
      "year": 2025,
      "month": 5,
      "day": 30,
      "extraInfo": "初四",
      "monthStartWeekIndex": 0,
      "monthEndWeekIndex": 5,
      "shiftType": 0,
      "agenda": []
    },
    {
      "year": 2025,
      "month": 5,
      "day": 31,
      "extraInfo": "端午节",
      "monthStartWeekIndex": 0,
      "monthEndWeekIndex": 5,
      "shiftType": 2,
      "agenda": []
    }
  ],
  [
    {
      "year": 2025,
      "month": 6,
      "day": 1,
      "extraInfo": "初六",
      "monthStartWeekIndex": 5,
      "monthEndWeekIndex": 10,
      "shiftType": 2,
      "agenda": []
    },
    {
      "year": 2025,
      "month": 6,
      "day": 2,
      "extraInfo": "初七",
      "monthStartWeekIndex": 5,
      "monthEndWeekIndex": 10,
      "shiftType": 2,
      "agenda": []
    },
    {
      "year": 2025,
      "month": 6,
      "day": 3,
      "extraInfo": "初八",
      "monthStartWeekIndex": 5,
      "monthEndWeekIndex": 10,
      "shiftType": 0,
      "agenda": []
    },
    {
      "year": 2025,
      "month": 6,
      "day": 4,
      "extraInfo": "初九",
      "monthStartWeekIndex": 5,
      "monthEndWeekIndex": 10,
      "shiftType": 0,
      "agenda": []
    },
    {
      "year": 2025,
      "month": 6,
      "day": 5,
      "extraInfo": "芒种",
      "monthStartWeekIndex": 5,
      "monthEndWeekIndex": 10,
      "shiftType": 0,
      "agenda": []
    },
    {
      "year": 2025,
      "month": 6,
      "day": 6,
      "extraInfo": "十一",
      "monthStartWeekIndex": 5,
      "monthEndWeekIndex": 10,
      "shiftType": 0,
      "agenda": []
    },
    {
      "year": 2025,
      "month": 6,
      "day": 7,
      "extraInfo": "十二",
      "monthStartWeekIndex": 5,
      "monthEndWeekIndex": 10,
      "shiftType": 0,
      "agenda": []
    }
  ],
  [
    {
      "year": 2025,
      "month": 6,
      "day": 8,
      "extraInfo": "十三",
      "monthStartWeekIndex": 5,
      "monthEndWeekIndex": 10,
      "shiftType": 0,
      "agenda": []
    },
    {
      "year": 2025,
      "month": 6,
      "day": 9,
      "extraInfo": "十四",
      "monthStartWeekIndex": 5,
      "monthEndWeekIndex": 10,
      "shiftType": 0,
      "agenda": []
    },
    {
      "year": 2025,
      "month": 6,
      "day": 10,
      "extraInfo": "十五",
      "monthStartWeekIndex": 5,
      "monthEndWeekIndex": 10,
      "shiftType": 0,
      "agenda": []
    },
    {
      "year": 2025,
      "month": 6,
      "day": 11,
      "extraInfo": "十六",
      "monthStartWeekIndex": 5,
      "monthEndWeekIndex": 10,
      "shiftType": 0,
      "agenda": []
    },
    {
      "year": 2025,
      "month": 6,
      "day": 12,
      "extraInfo": "十七",
      "monthStartWeekIndex": 5,
      "monthEndWeekIndex": 10,
      "shiftType": 0,
      "agenda": []
    },
    {
      "year": 2025,
      "month": 6,
      "day": 13,
      "extraInfo": "十八",
      "monthStartWeekIndex": 5,
      "monthEndWeekIndex": 10,
      "shiftType": 0,
      "agenda": []
    },
    {
      "year": 2025,
      "month": 6,
      "day": 14,
      "extraInfo": "十九",
      "monthStartWeekIndex": 5,
      "monthEndWeekIndex": 10,
      "shiftType": 0,
      "agenda": []
    }
  ],
  [
    {
      "year": 2025,
      "month": 6,
      "day": 15,
      "extraInfo": "二十",
      "monthStartWeekIndex": 5,
      "monthEndWeekIndex": 10,
      "shiftType": 0,
      "agenda": []
    },
    {
      "year": 2025,
      "month": 6,
      "day": 16,
      "extraInfo": "廿一",
      "monthStartWeekIndex": 5,
      "monthEndWeekIndex": 10,
      "shiftType": 0,
      "agenda": []
    },
    {
      "year": 2025,
      "month": 6,
      "day": 17,
      "extraInfo": "廿二",
      "monthStartWeekIndex": 5,
      "monthEndWeekIndex": 10,
      "shiftType": 0,
      "agenda": []
    },
    {
      "year": 2025,
      "month": 6,
      "day": 18,
      "extraInfo": "廿三",
      "monthStartWeekIndex": 5,
      "monthEndWeekIndex": 10,
      "shiftType": 0,
      "agenda": []
    },
    {
      "year": 2025,
      "month": 6,
      "day": 19,
      "extraInfo": "廿四",
      "monthStartWeekIndex": 5,
      "monthEndWeekIndex": 10,
      "shiftType": 0,
      "agenda": []
    },
    {
      "year": 2025,
      "month": 6,
      "day": 20,
      "extraInfo": "廿五",
      "monthStartWeekIndex": 5,
      "monthEndWeekIndex": 10,
      "shiftType": 0,
      "agenda": []
    },
    {
      "year": 2025,
      "month": 6,
      "day": 21,
      "extraInfo": "夏至",
      "monthStartWeekIndex": 5,
      "monthEndWeekIndex": 10,
      "shiftType": 0,
      "agenda": []
    }
  ],
  [
    {
      "year": 2025,
      "month": 6,
      "day": 22,
      "extraInfo": "廿七",
      "monthStartWeekIndex": 5,
      "monthEndWeekIndex": 10,
      "shiftType": 0,
      "agenda": []
    },
    {
      "year": 2025,
      "month": 6,
      "day": 23,
      "extraInfo": "廿八",
      "monthStartWeekIndex": 5,
      "monthEndWeekIndex": 10,
      "shiftType": 0,
      "agenda": []
    },
    {
      "year": 2025,
      "month": 6,
      "day": 24,
      "extraInfo": "廿九",
      "monthStartWeekIndex": 5,
      "monthEndWeekIndex": 10,
      "shiftType": 0,
      "agenda": []
    },
    {
      "year": 2025,
      "month": 6,
      "day": 25,
      "extraInfo": "六月",
      "monthStartWeekIndex": 5,
      "monthEndWeekIndex": 10,
      "shiftType": 0,
      "agenda": []
    },
    {
      "year": 2025,
      "month": 6,
      "day": 26,
      "extraInfo": "初二",
      "monthStartWeekIndex": 5,
      "monthEndWeekIndex": 10,
      "shiftType": 0,
      "agenda": []
    },
    {
      "year": 2025,
      "month": 6,
      "day": 27,
      "extraInfo": "初三",
      "monthStartWeekIndex": 5,
      "monthEndWeekIndex": 10,
      "shiftType": 0,
      "agenda": []
    },
    {
      "year": 2025,
      "month": 6,
      "day": 28,
      "extraInfo": "初四",
      "monthStartWeekIndex": 5,
      "monthEndWeekIndex": 10,
      "shiftType": 0,
      "agenda": []
    }
  ],
  [
    {
      "year": 2025,
      "month": 6,
      "day": 29,
      "extraInfo": "初五",
      "monthStartWeekIndex": 5,
      "monthEndWeekIndex": 10,
      "shiftType": 0,
      "agenda": []
    },
    {
      "year": 2025,
      "month": 6,
      "day": 30,
      "extraInfo": "初六",
      "monthStartWeekIndex": 5,
      "monthEndWeekIndex": 10,
      "shiftType": 0,
      "agenda": []
    },
    {
      "year": 2025,
      "month": 7,
      "day": 1,
      "extraInfo": "初七",
      "monthStartWeekIndex": 9,
      "monthEndWeekIndex": 14,
      "shiftType": 0,
      "agenda": []
    },
    {
      "year": 2025,
      "month": 7,
      "day": 2,
      "extraInfo": "初八",
      "monthStartWeekIndex": 9,
      "monthEndWeekIndex": 14,
      "shiftType": 0,
      "agenda": []
    },
    {
      "year": 2025,
      "month": 7,
      "day": 3,
      "extraInfo": "初九",
      "monthStartWeekIndex": 9,
      "monthEndWeekIndex": 14,
      "shiftType": 0,
      "agenda": []
    },
    {
      "year": 2025,
      "month": 7,
      "day": 4,
      "extraInfo": "初十",
      "monthStartWeekIndex": 9,
      "monthEndWeekIndex": 14,
      "shiftType": 0,
      "agenda": []
    },
    {
      "year": 2025,
      "month": 7,
      "day": 5,
      "extraInfo": "十一",
      "monthStartWeekIndex": 9,
      "monthEndWeekIndex": 14,
      "shiftType": 0,
      "agenda": []
    }
  ],
  [
    {
      "year": 2025,
      "month": 7,
      "day": 6,
      "extraInfo": "十二",
      "monthStartWeekIndex": 9,
      "monthEndWeekIndex": 14,
      "shiftType": 0,
      "agenda": []
    },
    {
      "year": 2025,
      "month": 7,
      "day": 7,
      "extraInfo": "小暑",
      "monthStartWeekIndex": 9,
      "monthEndWeekIndex": 14,
      "shiftType": 0,
      "agenda": []
    },
    {
      "year": 2025,
      "month": 7,
      "day": 8,
      "extraInfo": "十四",
      "monthStartWeekIndex": 9,
      "monthEndWeekIndex": 14,
      "shiftType": 0,
      "agenda": []
    },
    {
      "year": 2025,
      "month": 7,
      "day": 9,
      "extraInfo": "十五",
      "monthStartWeekIndex": 9,
      "monthEndWeekIndex": 14,
      "shiftType": 0,
      "agenda": []
    },
    {
      "year": 2025,
      "month": 7,
      "day": 10,
      "extraInfo": "十六",
      "monthStartWeekIndex": 9,
      "monthEndWeekIndex": 14,
      "shiftType": 0,
      "agenda": []
    },
    {
      "year": 2025,
      "month": 7,
      "day": 11,
      "extraInfo": "十七",
      "monthStartWeekIndex": 9,
      "monthEndWeekIndex": 14,
      "shiftType": 0,
      "agenda": []
    },
    {
      "year": 2025,
      "month": 7,
      "day": 12,
      "extraInfo": "十八",
      "monthStartWeekIndex": 9,
      "monthEndWeekIndex": 14,
      "shiftType": 0,
      "agenda": []
    }
  ],
  [
    {
      "year": 2025,
      "month": 7,
      "day": 13,
      "extraInfo": "十九",
      "monthStartWeekIndex": 9,
      "monthEndWeekIndex": 14,
      "shiftType": 0,
      "agenda": []
    },
    {
      "year": 2025,
      "month": 7,
      "day": 14,
      "extraInfo": "二十",
      "monthStartWeekIndex": 9,
      "monthEndWeekIndex": 14,
      "shiftType": 0,
      "agenda": []
    },
    {
      "year": 2025,
      "month": 7,
      "day": 15,
      "extraInfo": "廿一",
      "monthStartWeekIndex": 9,
      "monthEndWeekIndex": 14,
      "shiftType": 0,
      "agenda": []
    },
    {
      "year": 2025,
      "month": 7,
      "day": 16,
      "extraInfo": "廿二",
      "monthStartWeekIndex": 9,
      "monthEndWeekIndex": 14,
      "shiftType": 0,
      "agenda": []
    },
    {
      "year": 2025,
      "month": 7,
      "day": 17,
      "extraInfo": "廿三",
      "monthStartWeekIndex": 9,
      "monthEndWeekIndex": 14,
      "shiftType": 0,
      "agenda": []
    },
    {
      "year": 2025,
      "month": 7,
      "day": 18,
      "extraInfo": "廿四",
      "monthStartWeekIndex": 9,
      "monthEndWeekIndex": 14,
      "shiftType": 0,
      "agenda": []
    },
    {
      "year": 2025,
      "month": 7,
      "day": 19,
      "extraInfo": "廿五",
      "monthStartWeekIndex": 9,
      "monthEndWeekIndex": 14,
      "shiftType": 0,
      "agenda": []
    }
  ],
  [
    {
      "year": 2025,
      "month": 7,
      "day": 20,
      "extraInfo": "廿六",
      "monthStartWeekIndex": 9,
      "monthEndWeekIndex": 14,
      "shiftType": 0,
      "agenda": []
    },
    {
      "year": 2025,
      "month": 7,
      "day": 21,
      "extraInfo": "廿七",
      "monthStartWeekIndex": 9,
      "monthEndWeekIndex": 14,
      "shiftType": 0,
      "agenda": []
    },
    {
      "year": 2025,
      "month": 7,
      "day": 22,
      "extraInfo": "大暑",
      "monthStartWeekIndex": 9,
      "monthEndWeekIndex": 14,
      "shiftType": 0,
      "agenda": []
    },
    {
      "year": 2025,
      "month": 7,
      "day": 23,
      "extraInfo": "廿九",
      "monthStartWeekIndex": 9,
      "monthEndWeekIndex": 14,
      "shiftType": 0,
      "agenda": []
    },
    {
      "year": 2025,
      "month": 7,
      "day": 24,
      "extraInfo": "三十",
      "monthStartWeekIndex": 9,
      "monthEndWeekIndex": 14,
      "shiftType": 0,
      "agenda": []
    },
    {
      "year": 2025,
      "month": 7,
      "day": 25,
      "extraInfo": "闰六月",
      "monthStartWeekIndex": 9,
      "monthEndWeekIndex": 14,
      "shiftType": 0,
      "agenda": []
    },
    {
      "year": 2025,
      "month": 7,
      "day": 26,
      "extraInfo": "初二",
      "monthStartWeekIndex": 9,
      "monthEndWeekIndex": 14,
      "shiftType": 0,
      "agenda": []
    }
  ],
  [
    {
      "year": 2025,
      "month": 7,
      "day": 27,
      "extraInfo": "初三",
      "monthStartWeekIndex": 9,
      "monthEndWeekIndex": 14,
      "shiftType": 0,
      "agenda": []
    },
    {
      "year": 2025,
      "month": 7,
      "day": 28,
      "extraInfo": "初四",
      "monthStartWeekIndex": 9,
      "monthEndWeekIndex": 14,
      "shiftType": 0,
      "agenda": []
    },
    {
      "year": 2025,
      "month": 7,
      "day": 29,
      "extraInfo": "初五",
      "monthStartWeekIndex": 9,
      "monthEndWeekIndex": 14,
      "shiftType": 0,
      "agenda": []
    },
    {
      "year": 2025,
      "month": 7,
      "day": 30,
      "extraInfo": "初六",
      "monthStartWeekIndex": 9,
      "monthEndWeekIndex": 14,
      "shiftType": 0,
      "agenda": []
    },
    {
      "year": 2025,
      "month": 7,
      "day": 31,
      "extraInfo": "初七",
      "monthStartWeekIndex": 9,
      "monthEndWeekIndex": 14,
      "shiftType": 0,
      "agenda": []
    },
    {
      "year": 2025,
      "month": 8,
      "day": 1,
      "extraInfo": "初八",
      "monthStartWeekIndex": 9,
      "monthEndWeekIndex": 14,
      "shiftType": 0,
      "agenda": []
    },
    {
      "year": 2025,
      "month": 8,
      "day": 2,
      "extraInfo": "初九",
      "monthStartWeekIndex": 9,
      "monthEndWeekIndex": 14,
      "shiftType": 0,
      "agenda": []
    }
  ]
]